setup.cfg
setup.py
hippodclient/__init__.py
hippodclient/hippodclient.py
hippodclient.egg-info/PKG-INFO
hippodclient.egg-info/SOURCES.txt
hippodclient.egg-info/dependency_links.txt
hippodclient.egg-info/not-zip-safe
hippodclient.egg-info/top_level.txt